BuildBinary.py
PythonProjectBootstrapperTest20240403/EntryPoint.py
PythonProjectBootstrapperTest20240403/Math.py
PythonProjectBootstrapperTest20240403/__init__.py
PythonProjectBootstrapperTest20240403-0.1.1.dist-info/LICENSE.txt
PythonProjectBootstrapperTest20240403-0.1.1.dist-info/METADATA
PythonProjectBootstrapperTest20240403-0.1.1.dist-info/WHEEL
PythonProjectBootstrapperTest20240403-0.1.1.dist-info/entry_points.txt
PythonProjectBootstrapperTest20240403-0.1.1.dist-info/top_level.txt
PythonProjectBootstrapperTest20240403-0.1.1.dist-info/RECORD
